<!-- Copyright (c) 2021, Oracle and/or its affiliates. -->
<!-- Licensed under the Universal Permissive License v 1.0 as shown at https://oss.oracle.com/licenses/upl. -->
<weblogic-web-app xmlns="http://xmlns.oracle.com/weblogic/weblogic-web-app">
	<context-root>wls-exporter</context-root>
	<container-descriptor>
		<prefer-application-packages>
		   <package-name>com.google.gson.*</package-name>
		   <package-name>javax.inject.*</package-name>
		   <package-name>org.apache.commons.*</package-name>
		   <package-name>org.apache.http.*</package-name>
		   <package-name>org.glassfish.hk2.*</package-name>
		   <package-name>org.jvnet.hk2.*</package-name>
		   <package-name>org.jvnet.tiger_types.*</package-name>
		   <package-name>org.yaml.snakeyaml.*</package-name>
		</prefer-application-packages>
	</container-descriptor>
</weblogic-web-app>

